pke/__init__.py
pke/base.py
pke/data_structures.py
pke/lang.py
pke/readers.py
pke/utils.py
pke/models/Kea-semeval2010.py3.pickle
pke/models/WINGNUS-semeval2010.py3.pickle
pke/models/df-semeval2010.tsv.gz
pke/models/lda-1000-semeval2010.py3.pickle.gz
pke/supervised/__init__.py
pke/supervised/api.py
pke/supervised/feature_based/__init__.py
pke/supervised/feature_based/kea.py
pke/supervised/feature_based/wingnus.py
pke/unsupervised/__init__.py
pke/unsupervised/graph_based/__init__.py
pke/unsupervised/graph_based/multipartiterank.py
pke/unsupervised/graph_based/positionrank.py
pke/unsupervised/graph_based/single_tpr.py
pke/unsupervised/graph_based/singlerank.py
pke/unsupervised/graph_based/textrank.py
pke/unsupervised/graph_based/topicrank.py
pke/unsupervised/statistical/__init__.py
pke/unsupervised/statistical/firstphrases.py
pke/unsupervised/statistical/kpminer.py
pke/unsupervised/statistical/tfidf.py
pke/unsupervised/statistical/yake.py
ccpke-2.0.0.dist-info/LICENCE.md
ccpke-2.0.0.dist-info/METADATA
ccpke-2.0.0.dist-info/WHEEL
ccpke-2.0.0.dist-info/top_level.txt
ccpke-2.0.0.dist-info/RECORD
