Metadata-Version: 2.1
Name: ccpke
Version: 2.0.0
Summary: Python Keyphrase Extraction module
Home-page: https://github.com/boudinfl/pke
Author: pke contributors
Author-email: florian.boudin@univ-nantes.fr
License: gnu
License-File: LICENCE.md
Requires-Dist: nltk
Requires-Dist: networkx
Requires-Dist: numpy
Requires-Dist: scipy
Requires-Dist: scikit-learn
Requires-Dist: unidecode
Requires-Dist: future
Requires-Dist: joblib
Requires-Dist: spacy (>=3.2.3)
